fh_tailwindcss/__init__.py
fh_tailwindcss/icon.py
fh_tailwindcss/modal.py
fh_tailwindcss/tailwind.py
fh_tailwindcss-0.0.3.dist-info/LICENSE
fh_tailwindcss-0.0.3.dist-info/METADATA
fh_tailwindcss-0.0.3.dist-info/WHEEL
fh_tailwindcss-0.0.3.dist-info/top_level.txt
fh_tailwindcss-0.0.3.dist-info/RECORD
