Metadata-Version: 2.1
Name: fh_tailwindcss
Version: 0.0.3
Summary: Tailwind CSS package for FastHTML.
Author-email: lmbelo <lucas.belo@live.com>
License:                                  Apache License
Classifier: Development Status :: 3 - Alpha
Classifier: Intended Audience :: Developers
Classifier: Topic :: Software Development :: Build Tools
Classifier: License :: OSI Approved :: Apache Software License
Classifier: Programming Language :: Python :: 3
License-File: LICENSE
Requires-Dist: python-fasthtml>=0.10.1
Provides-Extra: flowbite
Requires-Dist: fh_flowbite>=0.0.1; extra == "flowbite"
